postgresql_s3_clickhouse/__init__.py
postgresql_s3_clickhouse/postgresql_s3_clickhouse.py
pg_s3_ch_talenttech_oss-0.1.6.dist-info/LICENSE.txt
pg_s3_ch_talenttech_oss-0.1.6.dist-info/METADATA
pg_s3_ch_talenttech_oss-0.1.6.dist-info/WHEEL
pg_s3_ch_talenttech_oss-0.1.6.dist-info/top_level.txt
pg_s3_ch_talenttech_oss-0.1.6.dist-info/RECORD
