Metadata-Version: 2.1
Name: pg-s3-ch-talenttech-oss
Version: 0.1.6
Summary: TopMind PG S3 CH Helper
Home-page: https://github.com/severgroup-tt/topmind-commons
Author: Vadim Petrov
Author-email: v.petrov@talenttech.ru
License: MIT
Platform: UNKNOWN
Classifier: Programming Language :: Python :: 3
Classifier: License :: OSI Approved :: MIT License
Classifier: Operating System :: OS Independent
Requires-Python: >=3.6
License-File: LICENSE.txt
Requires-Dist: boto3
